django_inpi/__init__.py
django_inpi/api.py
django_inpi/apps.py
django_inpi/data.py
django_inpi/fields.py
django_inpi/forms.py
django_inpi/locale/fr/LC_MESSAGES/django.mo
django_inpi/locale/fr/LC_MESSAGES/django.po
django_inpi/migrations/__init__.py
django_inpi/templates/django_inpi/siren_form.html
django_inpi/templates/django_inpi/siret_form.html
django_inpi/views.py
django_inpi-0.4.1.dist-info/METADATA
django_inpi-0.4.1.dist-info/WHEEL
django_inpi-0.4.1.dist-info/licenses/LICENSE
django_inpi-0.4.1.dist-info/RECORD
