Metadata-Version: 2.4
Name: django-inpi
Version: 0.4.1
Summary: Get companies info by using INPI api.
License: GNU GPLv3
License-File: LICENSE
Author: Kapt dev team
Author-email: dev@kapt.mobi
Requires-Python: >=3.9
Classifier: License :: Other/Proprietary License
Classifier: Programming Language :: Python :: 3
Classifier: Programming Language :: Python :: 3.9
Classifier: Programming Language :: Python :: 3.10
Classifier: Programming Language :: Python :: 3.11
Classifier: Programming Language :: Python :: 3.12
Classifier: Programming Language :: Python :: 3.13
Classifier: Programming Language :: Python :: 3.14
Requires-Dist: Django (>2.2)
Requires-Dist: luhncheck (>=2.2.0,<3.0.0)
Requires-Dist: mureq (==0.*)
Project-URL: Repository, https://gitlab.com/kapt/open-source/django-inpi
